{
    " ": 2517870,
    "田": 328571,
    "山": 156857,
    "大": 151558,
    "野": 144782,
    "藤": 132047,
    "川": 128748,
    "井": 117393,
    "太": 115809,
    "美": 112405,
    "小": 105870,
    "本": 102752,
    "村": 97012,
    "木": 89054,
    "原": 87800,
    "奈": 85550,
    "子": 82959,
    "中": 79370,
    "真": 77908,
    "菜": 77103,
    "香": 72902,
    "谷": 70769,
    "優": 69611,
    "松": 66885,
    "花": 66818,
    "高": 62825,
    "里": 59343,
    "希": 55951,
    "岡": 55748,
    "島": 55476,
    "平": 55389,
    "澤": 54690,
    "崎": 53930,
    "上": 52202,
    "海": 50931,
    "愛": 50271,
    "斗": 49156,
    "一": 46991,
    "口": 46924,
    "佐": 46466,
    "人": 45451,
    "石": 45137,
    "和": 44326,
    "也": 44294,
    "乃": 44219,
    "輝": 44115,
    "樹": 42464,
    "佳": 42351,
    "音": 42139,
    "西": 42049,
    "宮": 40513,
    "郎": 40469,
    "吉": 40442,
    "橋": 39780,
    "彩": 38748,
    "翔": 38538,
    "生": 38503,
    "内": 38203,
    "森": 36238,
    "夏": 36234,
    "下": 35278,
    "実": 34018,
    "々": 33971,
    "久": 33553,
    "永": 33230,
    "悠": 32951,
    "三": 32475,
    "介": 31924,
    "坂": 31281,
    "莉": 31068,
    "林": 30927,
    "千": 30863,
    "部": 30647,
    "梨": 30195,
    "陽": 30106,
    "貴": 30101,
    "華": 29104,
    "安": 29083,
    "加": 28936,
    "友": 28714,
    "尾": 28216,
    "祐": 28202,
    "岩": 27921,
    "伊": 27344,
    "哉": 26658,
    "未": 26653,
    "佑": 26625,
    "日": 26586,
    "紗": 26316,
    "理": 26192,
    "瀬": 25898,
    "長": 25728,
    "月": 25679,
    "鈴": 25658,
    "由": 25214,
    "志": 25211,
    "咲": 25167,
    "河": 24609,
    "弥": 24528,
    "智": 24384,
    "渡": 24101,
    "水": 24062,
    "拓": 23977,
    "江": 23935,
    "萌": 23755,
    "裕": 23436,
    "光": 22961,
    "紀": 22960,
    "那": 22938,
    "歩": 22907,
    "衣": 22884,
    "矢": 22452,
    "み": 22411,
    "羽": 22212,
    "金": 22195,
    "成": 21926,
    "明": 21894,
    "古": 21597,
    "有": 21572,
    "葉": 21519,
    "穂": 21513,
    "塚": 21305,
    "池": 20858,
    "竹": 20792,
    "沙": 20697,
    "馬": 20570,
    "結": 20471,
    "沢": 20412,
    "保": 20355,
    "福": 20350,
    "亜": 20199,
    "恵": 19865,
    "龍": 19673,
    "倉": 19562,
    "嶋": 19334,
    "津": 19248,
    "夢": 19189,
    "浦": 19187,
    "か": 19122,
    "武": 19075,
    "朗": 19068,
    "な": 19064,
    "之": 18858,
    "新": 18781,
    "雅": 18695,
    "南": 18588,
    "聖": 18471,
    "幸": 18419,
    "戸": 18414,
    "星": 18379,
    "り": 18217,
    "良": 17667,
    "瑠": 17606,
    "健": 17516,
    "汰": 17478,
    "杉": 17296,
    "央": 17036,
    "北": 16796,
    "麻": 16616,
    "帆": 16591,
    "来": 16531,
    "春": 16510,
    "間": 16464,
    "晴": 16414,
    "元": 16138,
    "涼": 16006,
    "知": 15916,
    "寺": 15628,
    "雄": 15607,
    "颯": 15545,
    "堀": 15462,
    "根": 15419,
    "直": 15289,
    "地": 15235,
    "今": 15228,
    "あ": 15037,
    "勇": 14979,
    "関": 14950,
    "清": 14766,
    "見": 14735,
    "黒": 14566,
    "城": 14523,
    "桜": 14426,
    "亮": 14268,
    "賀": 14191,
    "空": 14075,
    "史": 14074,
    "将": 13856,
    "遥": 13846,
    "玲": 13775,
    "侑": 13637,
    "仁": 13439,
    "吾": 13378,
    "桃": 13157,
    "横": 13148,
    "神": 13044,
    "茉": 12951,
    "琉": 12932,
    "竜": 12854,
    "輔": 12841,
    "杏": 12780,
    "前": 12739,
    "東": 12657,
    "心": 12638,
    "青": 12586,
    "丸": 12581,
    "楓": 12383,
    "柳": 12267,
    "綾": 12256,
    "沼": 12146,
    "奥": 11948,
    "屋": 11922,
    "辺": 11903,
    "阿": 11785,
    "唯": 11748,
    "航": 11699,
    "果": 11672,
    "晃": 11667,
    "都": 11663,
    "瑞": 11655,
    "怜": 11629,
    "士": 11620,
    "緒": 11549,
    "隆": 11521,
    "駿": 11473,
    "多": 11323,
    "土": 11275,
    "泉": 11029,
    "白": 10979,
    "秋": 10943,
    "依": 10789,
    "泰": 10788,
    "英": 10715,
    "司": 10714,
    "ひ": 10697,
    "波": 10694,
    "広": 10678,
    "七": 10601,
    "秀": 10523,
    "宇": 10502,
    "風": 10469,
    "俊": 10408,
    "望": 10400,
    "菅": 10381,
    "須": 10380,
    "利": 10376,
    "季": 10237,
    "畑": 10209,
    "琴": 10201,
    "荒": 10196,
    "早": 10165,
    "浅": 10156,
    "名": 10149,
    "飯": 10091,
    "舞": 10075,
    "純": 10015,
    "稲": 9999,
    "天": 9894,
    "織": 9892,
    "葵": 9829,
    "康": 9817,
    "百": 9811,
    "の": 9807,
    "陸": 9774,
    "ゆ": 9749,
    "市": 9720,
    "若": 9696,
    "正": 9686,
    "さ": 9672,
    "岸": 9612,
    "向": 9591,
    "越": 9542,
    "遠": 9385,
    "弘": 9354,
    "喜": 9245,
    "璃": 9198,
    "登": 9195,
    "二": 9185,
    "菊": 9107,
    "出": 8997,
    "隼": 8979,
    "凌": 8963,
    "熊": 8956,
    "尚": 8950,
    "芽": 8874,
    "垣": 8676,
    "柚": 8641,
    "世": 8538,
    "稀": 8493,
    "場": 8467,
    "珠": 8446,
    "濱": 8398,
    "玉": 8387,
    "栗": 8332,
    "勝": 8294,
    "圭": 8265,
    "ら": 8254,
    "徳": 8250,
    "柴": 8194,
    "誠": 8179,
    "近": 8087,
    "朋": 8074,
    "達": 7941,
    "後": 7927,
    "蓮": 7900,
    "寛": 7894,
    "立": 7838,
    "凛": 7808,
    "る": 7797,
    "悟": 7758,
    "瑛": 7737,
    "米": 7735,
    "富": 7729,
    "合": 7713,
    "己": 7703,
    "凜": 7682,
    "赤": 7672,
    "代": 7651,
    "深": 7638,
    "慶": 7600,
    "絵": 7566,
    "い": 7527,
    "啓": 7513,
    "片": 7433,
    "塩": 7433,
    "八": 7407,
    "宏": 7386,
    "廣": 7366,
    "文": 7234,
    "こ": 7157,
    "朱": 7154,
    "飛": 7115,
    "治": 7102,
    "細": 7063,
    "柊": 7047,
    "蒼": 6981,
    "奏": 6936,
    "孝": 6923,
    "浩": 6919,
    "笠": 6897,
    "遼": 6870,
    "洋": 6858,
    "増": 6852,
    "ま": 6837,
    "妃": 6833,
    "相": 6724,
    "詩": 6706,
    "祥": 6699,
    "梅": 6634,
    "き": 6598,
    "五": 6584,
    "眞": 6563,
    "諒": 6480,
    "斉": 6444,
    "邉": 6393,
    "角": 6388,
    "浜": 6379,
    "麗": 6315,
    "篠": 6311,
    "基": 6271,
    "脇": 6223,
    "京": 6216,
    "齋": 6158,
    "磨": 6156,
    "辻": 6152,
    "重": 6125,
    "仲": 6104,
    "留": 6049,
    "暉": 5997,
    "豊": 5868,
    "門": 5862,
    "寿": 5855,
    "く": 5854,
    "万": 5841,
    "冨": 5837,
    "碧": 5809,
    "郁": 5797,
    "宗": 5786,
    "姫": 5776,
    "慎": 5687,
    "植": 5578,
    "栞": 5514,
    "手": 5479,
    "響": 5467,
    "鳥": 5467,
    "笹": 5458,
    "朝": 5440,
    "酒": 5411,
    "園": 5375,
    "磯": 5355,
    "桑": 5338,
    "道": 5326,
    "嘉": 5312,
    "夕": 5301,
    "賢": 5279,
    "洸": 5246,
    "牧": 5218,
    "叶": 5213,
    "耶": 5194,
    "十": 5191,
    "信": 5170,
    "紘": 5140,
    "虎": 5113,
    "雪": 5110,
    "亀": 5055,
    "恭": 5048,
    "匠": 5026,
    "も": 4994,
    "壮": 4970,
    "我": 4960,
    "家": 4948,
    "滝": 4839,
    "礼": 4829,
    "斎": 4823,
    "は": 4805,
    "昂": 4718,
    "邊": 4703,
    "渕": 4697,
    "玖": 4679,
    "李": 4663,
    "工": 4662,
    "凪": 4639,
    "稜": 4631,
    "絢": 4627,
    "梶": 4600,
    "流": 4575,
    "つ": 4556,
    "方": 4498,
    "枝": 4496,
    "末": 4446,
    "比": 4416,
    "鶴": 4340,
    "慧": 4322,
    "尋": 4303,
    "室": 4259,
    "ず": 4224,
    "聡": 4218,
    "櫻": 4178,
    "修": 4163,
    "翼": 4144,
    "敬": 4143,
    "博": 4141,
    "滉": 4134,
    "紅": 4133,
    "吹": 4120,
    "哲": 4112,
    "義": 4097,
    "羅": 4095,
    "次": 4079,
    "歌": 4052,
    "作": 4034,
    "晟": 4004,
    "澄": 3952,
    "守": 3932,
    "ノ": 3918,
    "板": 3910,
    "茂": 3872,
    "彦": 3856,
    "瀧": 3835,
    "寧": 3809,
    "可": 3807,
    "町": 3797,
    "好": 3791,
    "嵐": 3786,
    "曽": 3768,
    "住": 3758,
    "幹": 3755,
    "居": 3750,
    "伸": 3746,
    "萩": 3745,
    "温": 3738,
    "ん": 3734,
    "巧": 3697,
    "皓": 3678,
    "樋": 3676,
    "崇": 3655,
    "草": 3653,
    "桐": 3637,
    "伶": 3625,
    "敦": 3621,
    "剛": 3620,
    "鎌": 3563,
    "渚": 3561,
    "周": 3529,
    "畠": 3515,
    "藍": 3497,
    "國": 3484,
    "汐": 3482,
    "端": 3475,
    "満": 3463,
    "児": 3460,
    "楽": 3446,
    "す": 3444,
    "入": 3439,
    "溝": 3438,
    "丹": 3395,
    "荻": 3372,
    "坪": 3362,
    "湯": 3362,
    "綺": 3355,
    "芳": 3327,
    "鹿": 3312,
    "行": 3290,
    "昌": 3280,
    "阪": 3268,
    "典": 3225,
    "政": 3218,
    "貫": 3217,
    "榎": 3215,
    "や": 3211,
    "う": 3205,
    "紫": 3193,
    "琳": 3189,
    "目": 3180,
    "蘭": 3160,
    "力": 3157,
    "丈": 3148,
    "ほ": 3146,
    "克": 3134,
    "瑚": 3112,
    "公": 3088,
    "倫": 3087,
    "形": 3075,
    "船": 3060,
    "甲": 3053,
    "功": 3052,
    "淳": 3051,
    "路": 3046,
    "と": 3011,
    "兼": 3011,
    "庄": 3004,
    "国": 3004,
    "砂": 3002,
    "舘": 2997,
    "條": 2994,
    "冬": 2994,
    "猪": 2993,
    "巳": 2974,
    "湧": 2966,
    "伽": 2962,
    "柿": 2950,
    "栄": 2938,
    "岳": 2929,
    "嶺": 2917,
    "晶": 2894,
    "快": 2892,
    "郷": 2880,
    "ろ": 2867,
    "笑": 2867,
    "齊": 2866,
    "吏": 2864,
    "彰": 2849,
    "峻": 2840,
    "魁": 2831,
    "宙": 2821,
    "窪": 2814,
    "巻": 2797,
    "貝": 2794,
    "耀": 2789,
    "弓": 2761,
    "恋": 2748,
    "え": 2737,
    "篤": 2726,
    "柏": 2707,
    "冴": 2698,
    "開": 2697,
    "宅": 2696,
    "茜": 2694,
    "沖": 2663,
    "暖": 2662,
    "外": 2639,
    "ち": 2619,
    "助": 2615,
    "昇": 2591,
    "潤": 2588,
    "お": 2588,
    "服": 2578,
    "澪": 2575,
    "瞳": 2560,
    "椋": 2560,
    "創": 2534,
    "輪": 2530,
    "章": 2527,
    "卓": 2514,
    "幡": 2512,
    "た": 2507,
    "起": 2498,
    "楠": 2496,
    "蔵": 2492,
    "庭": 2476,
    "れ": 2473,
    "虹": 2458,
    "納": 2456,
    "渋": 2444,
    "采": 2443,
    "持": 2442,
    "杜": 2424,
    "尻": 2424,
    "爽": 2389,
    "堂": 2364,
    "恒": 2361,
    "憲": 2343,
    "胡": 2339,
    "駒": 2338,
    "頭": 2328,
    "辰": 2313,
    "峰": 2310,
    "時": 2309,
    "初": 2301,
    "睦": 2294,
    "牛": 2291,
    "足": 2274,
    "渉": 2264,
    "俣": 2262,
    "映": 2252,
    "毛": 2246,
    "謙": 2241,
    "進": 2241,
    "迫": 2233,
    "斐": 2231,
    "舜": 2224,
    "め": 2209,
    "征": 2206,
    "凱": 2205,
    "盛": 2190,
    "又": 2184,
    "能": 2182,
    "薫": 2160,
    "添": 2157,
    "乙": 2143,
    "偉": 2141,
    "毅": 2139,
    "遙": 2133,
    "老": 2133,
    "廉": 2124,
    "照": 2115,
    "峯": 2109,
    "脩": 2097,
    "芝": 2067,
    "恩": 2064,
    "彪": 2059,
    "惟": 2053,
    "樫": 2046,
    "規": 2042,
    "し": 2024,
    "桂": 2017,
    "暁": 2005,
    "静": 1994,
    "布": 1986,
    "芹": 1981,
    "嵩": 1972,
    "伯": 1970,
    "榊": 1962,
    "四": 1955,
    "琢": 1946,
    "騎": 1944,
    "伍": 1941,
    "慈": 1936,
    "湖": 1934,
    "勢": 1934,
    "臼": 1932,
    "捺": 1920,
    "芦": 1920,
    "及": 1917,
    "鬼": 1914,
    "円": 1887,
    "耕": 1883,
    "椎": 1876,
    "鍋": 1859,
    "諸": 1854,
    "豪": 1841,
    "景": 1840,
    "落": 1837,
    "葛": 1837,
    "摘": 1834,
    "倖": 1831,
    "充": 1829,
    "よ": 1826,
    "益": 1811,
    "所": 1800,
    "崚": 1780,
    "壱": 1780,
    "鷹": 1771,
    "槻": 1770,
    "善": 1757,
    "狩": 1749,
    "匡": 1743,
    "妻": 1743,
    "皆": 1728,
    "尊": 1726,
    "透": 1707,
    "雛": 1703,
    "旺": 1696,
    "リ": 1694,
    "摩": 1692,
    "呂": 1680,
    "気": 1676,
    "ね": 1675,
    "建": 1666,
    "鵜": 1663,
    "堤": 1661,
    "椰": 1622,
    "奨": 1619,
    "舟": 1616,
    "源": 1586,
    "並": 1578,
    "嗣": 1566,
    "づ": 1562,
    "橘": 1559,
    "雨": 1555,
    "玄": 1543,
    "糸": 1529,
    "堅": 1528,
    "切": 1521,
    "常": 1512,
    "折": 1511,
    "梓": 1508,
    "押": 1507,
    "育": 1495,
    "雲": 1495,
    "苗": 1488,
    "竣": 1486,
    "右": 1481,
    "半": 1475,
    "維": 1469,
    "敏": 1445,
    "ど": 1441,
    "靖": 1436,
    "取": 1434,
    "築": 1428,
    "宥": 1416,
    "薗": 1411,
    "浪": 1390,
    "旭": 1374,
    "飼": 1373,
    "嵜": 1366,
    "徹": 1364,
    "味": 1347,
    "以": 1335,
    "惇": 1334,
    "憂": 1332,
    "威": 1326,
    "兵": 1323,
    "女": 1319,
    "科": 1297,
    "想": 1295,
    "ヶ": 1291,
    "記": 1282,
    "瞭": 1281,
    "昴": 1281,
    "奎": 1279,
    "亘": 1278,
    "ナ": 1278,
    "巴": 1268,
    "僚": 1264,
    "宝": 1263,
    "至": 1260,
    "渓": 1257,
    "御": 1257,
    "昭": 1254,
    "樺": 1253,
    "染": 1247,
    "鷲": 1243,
    "芙": 1242,
    "郡": 1241,
    "來": 1232,
    "誉": 1231,
    "引": 1226,
    "筒": 1221,
    "晏": 1216,
    "淵": 1214,
    "ア": 1198,
    "揮": 1197,
    "拳": 1194,
    "唐": 1187,
    "粟": 1179,
    "ぐ": 1175,
    "稔": 1171,
    "影": 1169,
    "晋": 1166,
    "頼": 1165,
    "王": 1164,
    "梧": 1161,
    "品": 1136,
    "ケ": 1133,
    "種": 1121,
    "茅": 1108,
    "苑": 1096,
    "緋": 1093,
    "犬": 1091,
    "肥": 1087,
    "柾": 1084,
    "氏": 1083,
    "主": 1079,
    "ン": 1074,
    "師": 1071,
    "仙": 1067,
    "綿": 1061,
    "遊": 1060,
    "黎": 1054,
    "敷": 1046,
    "伏": 1038,
    "分": 1035,
    "爪": 1035,
    "翠": 1034,
    "釜": 1031,
    "宍": 1026,
    "そ": 1023,
    "朔": 1016,
    "諏": 1015,
    "銀": 1014,
    "棚": 1009,
    "掛": 1002,
    "暮": 1001,
    "於": 996,
    "丞": 992,
    "逸": 990,
    "祈": 989,
    "鴨": 988,
    "臣": 986,
    "則": 982,
    "延": 982,
    "連": 982,
    "カ": 980,
    "穏": 973,
    "瓶": 971,
    "穴": 968,
    "張": 967,
    "緑": 965,
    "零": 963,
    "隈": 963,
    "陵": 960,
    "置": 950,
    "順": 949,
    "詠": 939,
    "皐": 938,
    "忠": 936,
    "会": 935,
    "麟": 926,
    "訪": 926,
    "蒲": 922,
    "令": 920,
    "澁": 918,
    "瞬": 916,
    "難": 915,
    "統": 915,
    "別": 914,
    "岐": 910,
    "府": 910,
    "宜": 908,
    "君": 908,
    "槙": 907,
    "ル": 906,
    "定": 905,
    "隅": 903,
    "鉄": 899,
    "紺": 891,
    "イ": 888,
    "彬": 888,
    "律": 882,
    "境": 880,
    "苅": 877,
    "嶌": 874,
    "法": 873,
    "孔": 868,
    "喬": 865,
    "網": 857,
    "舩": 857,
    "馨": 855,
    "弦": 854,
    "惠": 853,
    "蒔": 852,
    "厚": 850,
    "わ": 845,
    "椿": 845,
    "座": 842,
    "込": 836,
    "皇": 833,
    "鴻": 830,
    "檜": 822,
    "綱": 815,
    "秦": 814,
    "顕": 813,
    "邑": 812,
    "菱": 811,
    "鳴": 810,
    "榛": 809,
    "積": 806,
    "薄": 804,
    "学": 798,
    "腰": 796,
    "与": 794,
    "洲": 784,
    "倭": 780,
    "剣": 777,
    "鮎": 776,
    "淺": 775,
    "針": 767,
    "亨": 763,
    "左": 759,
    "牟": 758,
    "茄": 753,
    "迅": 748,
    "岬": 744,
    "レ": 742,
    "串": 742,
    "瑶": 741,
    "鼓": 740,
    "夜": 738,
    "貞": 738,
    "埜": 737,
    "當": 734,
    "湊": 732,
    "薮": 732,
    "色": 730,
    "漆": 728,
    "寄": 725,
    "興": 723,
    "夫": 723,
    "伴": 722,
    "ツ": 721,
    "股": 716,
    "袋": 716,
    "潮": 713,
    "紋": 713,
    "魚": 710,
    "ミ": 709,
    "数": 700,
    "駆": 697,
    "乾": 696,
    "壁": 696,
    "施": 696,
    "猿": 693,
    "六": 689,
    "衛": 687,
    "礒": 686,
    "要": 684,
    "男": 681,
    "環": 679,
    "繁": 673,
    "副": 673,
    "房": 671,
    "暢": 668,
    "せ": 668,
    "刀": 666,
    "才": 665,
    "権": 662,
    "允": 660,
    "更": 646,
    "堺": 642,
    "實": 642,
    "櫛": 638,
    "縄": 638,
    "研": 637,
    "護": 634,
    "甫": 632,
    "藪": 632,
    "稚": 629,
    "マ": 623,
    "粕": 620,
    "蛭": 619,
    "双": 618,
    "桝": 618,
    "茶": 617,
    "笙": 616,
    "藏": 616,
    "菫": 609,
    "首": 609,
    "範": 609,
    "条": 609,
    "箕": 606,
    "鳳": 603,
    "思": 600,
    "會": 599,
    "柄": 595,
    "煕": 590,
    "毬": 590,
    "捷": 587,
    "ば": 586,
    "総": 586,
    "覇": 585,
    "ラ": 574,
    "詰": 573,
    "宣": 572,
    "露": 569,
    "館": 569,
    "與": 568,
    "ふ": 566,
    "儀": 566,
    "塁": 561,
    "樂": 555,
    "享": 554,
    "詞": 553,
    "階": 550,
    "資": 550,
    "錦": 539,
    "荘": 537,
    "悦": 537,
    "萬": 535,
    "刈": 528,
    "栖": 526,
    "瑳": 526,
    "豆": 524,
    "ぎ": 521,
    "親": 521,
    "素": 520,
    "霜": 516,
    "渥": 512,
    "油": 511,
    "巣": 508,
    "尭": 507,
    "就": 506,
    "エ": 501,
    "洞": 500,
    "紳": 497,
    "媛": 496,
    "濃": 496,
    "萱": 495,
    "旗": 494,
    "務": 490,
    "冶": 490,
    "嵯": 489,
    "彗": 488,
    "宿": 488,
    "反": 488,
    "九": 488,
    "殿": 487,
    "的": 484,
    "楢": 483,
    "箱": 481,
    "卯": 481,
    "省": 477,
    "寒": 476,
    "雷": 476,
    "指": 475,
    "造": 472,
    "速": 471,
    "袴": 469,
    "莞": 468,
    "誓": 467,
    "樽": 467,
    "烈": 466,
    "了": 466,
    "妹": 465,
    "サ": 462,
    "畔": 461,
    "勘": 461,
    "綸": 458,
    "呉": 457,
    "番": 456,
    "黄": 453,
    "矩": 453,
    "架": 452,
    "是": 452,
    "蜂": 448,
    "紬": 445,
    "ぞ": 443,
    "鞠": 443,
    "邦": 442,
    "財": 437,
    "束": 435,
    "像": 435,
    "妙": 434,
    "通": 432,
    "菖": 431,
    "梁": 431,
    "鮫": 429,
    "準": 428,
    "最": 427,
    "錬": 426,
    "槇": 425,
    "蓑": 424,
    "縣": 423,
    "瓜": 422,
    "打": 422,
    "蛯": 422,
    "教": 422,
    "閑": 421,
    "籠": 420,
    "先": 418,
    "在": 417,
    "熙": 417,
    "梢": 416,
    "曲": 415,
    "圓": 415,
    "祖": 413,
    "孫": 413,
    "絹": 413,
    "陣": 413,
    "扇": 412,
    "念": 411,
    "頌": 410,
    "桶": 410,
    "塙": 409,
    "彌": 409,
    "燎": 404,
    "為": 404,
    "倍": 401,
    "面": 401,
    "鏡": 398,
    "絃": 396,
    "干": 390,
    "管": 390,
    "將": 389,
    "類": 388,
    "諄": 387,
    "霞": 386,
    "侃": 383,
    "碓": 382,
    "嬉": 378,
    "継": 377,
    "蕗": 376,
    "領": 375,
    "陶": 374,
    "峨": 373,
    "舛": 373,
    "む": 371,
    "具": 370,
    "車": 369,
    "乗": 364,
    "降": 362,
    "麦": 362,
    "集": 361,
    "憧": 361,
    "鐘": 361,
    "浮": 361,
    "鍵": 360,
    "沓": 360,
    "び": 358,
    "附": 356,
    "疋": 356,
    "愁": 356,
    "巽": 355,
    "オ": 355,
    "キ": 355,
    "に": 354,
    "ご": 354,
    "諭": 352,
    "鍛": 352,
    "升": 351,
    "栃": 350,
    "蛍": 349,
    "敢": 349,
    "對": 349,
    "狭": 348,
    "兒": 348,
    "床": 348,
    "絋": 347,
    "全": 347,
    "壽": 346,
    "惣": 346,
    "覚": 346,
    "ヒ": 345,
    "燿": 345,
    "ぶ": 345,
    "得": 343,
    "ユ": 343,
    "鯉": 343,
    "位": 342,
    "淑": 341,
    "榮": 341,
    "粋": 340,
    "甘": 339,
    "け": 337,
    "塔": 337,
    "紙": 337,
    "穣": 334,
    "蔭": 334,
    "任": 332,
    "猛": 331,
    "棟": 330,
    "呼": 330,
    "印": 328,
    "椛": 328,
    "孟": 327,
    "潟": 327,
    "坊": 327,
    "完": 326,
    "幾": 324,
    "伎": 323,
    "歳": 322,
    "涌": 319,
    "忍": 316,
    "で": 315,
    "じ": 314,
    "滋": 313,
    "ウ": 313,
    "息": 313,
    "碩": 312,
    "叡": 312,
    "際": 312,
    "考": 311,
    "年": 311,
    "設": 310,
    "如": 310,
    "ト": 310,
    "ス": 307,
    "灯": 307,
    "柘": 306,
    "軽": 305,
    "祝": 303,
    "然": 301,
    "鍬": 297,
    "民": 296,
    "只": 296,
    "昆": 295,
    "ょ": 295,
    "筑": 295,
    "観": 295,
    "余": 295,
    "嶽": 294,
    "欧": 293,
    "茨": 292,
    "寅": 292,
    "港": 292,
    "晨": 291,
    "薬": 290,
    "穐": 289,
    "銘": 288,
    "蟹": 286,
    "譲": 285,
    "ー": 284,
    "粂": 282,
    "胤": 282,
    "展": 281,
    "強": 281,
    "庸": 280,
    "蝦": 280,
    "桧": 280,
    "ゅ": 279,
    "ッ": 279,
    "衿": 278,
    "氣": 278,
    "佃": 278,
    "禮": 277,
    "畝": 276,
    "鉢": 275,
    "表": 275,
    "鼻": 273,
    "俵": 273,
    "州": 272,
    "熱": 272,
    "綜": 271,
    "侍": 271,
    "魅": 270,
    "轟": 270,
    "励": 269,
    "シ": 269,
    "播": 269,
    "物": 267,
    "旬": 267,
    "穗": 267,
    "意": 266,
    "杵": 265,
    "不": 265,
    "朴": 264,
    "荷": 263,
    "ジ": 263,
    "極": 261,
    "滑": 261,
    "垂": 260,
    "禎": 259,
    "両": 259,
    "泊": 255,
    "關": 255,
    "氷": 254,
    "箭": 251,
    "拡": 250,
    "鴫": 250,
    "各": 248,
    "削": 246,
    "偲": 246,
    "籾": 245,
    "晧": 244,
    "盤": 243,
    "欣": 243,
    "対": 243,
    "愉": 242,
    "聞": 241,
    "字": 241,
    "段": 241,
    "迪": 240,
    "赳": 240,
    "童": 239,
    "替": 237,
    "洵": 237,
    "鴇": 237,
    "藁": 234,
    "徒": 234,
    "コ": 230,
    "タ": 229,
    "経": 228,
    "准": 227,
    "練": 226,
    "逢": 226,
    "仮": 226,
    "鷺": 224,
    "父": 223,
    "院": 222,
    "詢": 222,
    "爾": 222,
    "笛": 222,
    "似": 221,
    "命": 221,
    "栢": 219,
    "裟": 219,
    "台": 219,
    "モ": 219,
    "謝": 219,
    "翁": 218,
    "寳": 218,
    "燦": 216,
    "檀": 216,
    "蓬": 216,
    "曾": 215,
    "ク": 215,
    "巨": 215,
    "亦": 214,
    "釣": 214,
    "旦": 213,
    "承": 212,
    "祭": 212,
    "糟": 211,
    "釘": 211,
    "禅": 210,
    "輿": 209,
    "漱": 208,
    "筋": 208,
    "籔": 207,
    "無": 206,
    "黛": 206,
    "母": 206,
    "予": 205,
    "稗": 205,
    "歓": 204,
    "貢": 203,
    "縁": 203,
    "汀": 202,
    "図": 202,
    "挙": 202,
    "丘": 201,
    "麿": 201,
    "緩": 200,
    "此": 199,
    "匂": 199,
    "纐": 199,
    "容": 199,
    "楯": 199,
    "鯨": 198,
    "軌": 198,
    "芥": 198,
    "臺": 198,
    "纈": 197,
    "繭": 195,
    "戎": 195,
    "燈": 194,
    "迎": 194,
    "言": 193,
    "程": 192,
    "淡": 191,
    "社": 191,
    "使": 191,
    "帝": 190,
    "姉": 190,
    "破": 189,
    "簗": 187,
    "枡": 187,
    "用": 186,
    "射": 186,
    "ニ": 186,
    "ヤ": 185,
    "途": 185,
    "鳩": 185,
    "筧": 185,
    "身": 184,
    "帯": 184,
    "籏": 184,
    "共": 184,
    "炭": 183,
    "邨": 183,
    "椙": 181,
    "峠": 181,
    "蔦": 181,
    "槌": 181,
    "幕": 180,
    "揚": 180,
    "傳": 180,
    "養": 179,
    "宰": 177,
    "走": 177,
    "計": 177,
    "雑": 177,
    "傑": 176,
    "畦": 175,
    "蘇": 175,
    "待": 175,
    "割": 174,
    "但": 173,
    "食": 173,
    "楊": 173,
    "訓": 172,
    "鏑": 172,
    "額": 171,
    "当": 171,
    "曜": 171,
    "袖": 169,
    "識": 169,
    "改": 169,
    "洗": 169,
    "農": 167,
    "税": 167,
    "伝": 167,
    "舎": 167,
    "塲": 167,
    "庵": 166,
    "幅": 165,
    "追": 165,
    "陰": 165,
    "勅": 164,
    "軍": 162,
    "皿": 162,
    "榑": 161,
    "策": 160,
    "冠": 160,
    "示": 159,
    "甚": 159,
    "厘": 158,
    "ロ": 158,
    "簑": 158,
    "應": 157,
    "ィ": 156,
    "苫": 155,
    "曳": 154,
    "洪": 154,
    "執": 154,
    "ハ": 153,
    "薙": 153,
    "ュ": 153,
    "銭": 152,
    "袈": 152,
    "弾": 151,
    "択": 150,
    "誌": 150,
    "肇": 149,
    "占": 149,
    "操": 149,
    "陳": 147,
    "愼": 146,
    "砥": 146,
    "到": 144,
    "菰": 144,
    "球": 143,
    "運": 142,
    "備": 142,
    "刺": 142,
    "銅": 141,
    "蓉": 140,
    "饗": 140,
    "普": 140,
    "灰": 138,
    "午": 138,
    "格": 137,
    "淀": 137,
    "粥": 137,
    "裏": 137,
    "碇": 136,
    "韻": 136,
    "圷": 135,
    "等": 135,
    "チ": 134,
    "視": 134,
    "式": 134,
    "逆": 133,
    "免": 133,
    "許": 133,
    "廻": 133,
    "跡": 132,
    "芸": 132,
    "禄": 132,
    "緯": 132,
    "灘": 131,
    "墨": 131,
    "活": 131,
    "亞": 131,
    "厨": 131,
    "火": 130,
    "祢": 130,
    "笈": 129,
    "界": 129,
    "薩": 129,
    "者": 128,
    "勲": 128,
    "勁": 128,
    "夛": 128,
    "済": 127,
    "札": 126,
    "鎗": 126,
    "尼": 126,
    "情": 125,
    "糠": 125,
    "壯": 124,
    "称": 123,
    "梠": 122,
    "篭": 122,
    "遵": 121,
    "軒": 121,
    "テ": 121,
    "セ": 120,
    "釼": 120,
    "尉": 120,
    "隠": 120,
    "旅": 120,
    "雫": 120,
    "働": 120,
    "付": 119,
    "瓦": 119,
    "掘": 118,
    "后": 117,
    "語": 117,
    "官": 117,
    "堯": 117,
    "桁": 116,
    "啄": 116,
    "懸": 116,
    "朽": 116,
    "韮": 116,
    "始": 115,
    "鞍": 115,
    "フ": 115,
    "醍": 115,
    "ム": 114,
    "鋤": 114,
    "霧": 113,
    "因": 113,
    "刑": 113,
    "箸": 113,
    "蒜": 112,
    "吟": 112,
    "卜": 112,
    "鎮": 111,
    "鑓": 110,
    "醐": 110,
    "続": 109,
    "器": 108,
    "申": 108,
    "耒": 108,
    "節": 107,
    "虻": 107,
    "誇": 107,
    "提": 107,
    "願": 106,
    "烏": 106,
    "昼": 105,
    "仕": 105,
    "憩": 105,
    "ョ": 105,
    "請": 104,
    "メ": 103,
    "瑤": 102,
    "量": 101,
    "仰": 101,
    "同": 101,
    "櫃": 101,
    "句": 100,
    "応": 100,
    "自": 100,
    "紹": 100,
    "礁": 99,
    "剱": 99,
    "厳": 98,
    "丁": 98,
    "埴": 97,
    "溜": 97,
    "累": 96,
    "紡": 96,
    "庫": 96,
    "発": 96,
    "て": 96,
    "度": 96,
    "ェ": 96,
    "喰": 95,
    "堰": 95,
    "互": 95,
    "現": 95,
    "讃": 95,
    "包": 95,
    "已": 95,
    "曉": 94,
    "努": 94,
    "塗": 94,
    "豫": 93,
    "督": 93,
    "雁": 93,
    "蕪": 93,
    "葭": 93,
    "覧": 92,
    "尽": 92,
    "諌": 92,
    "だ": 92,
    "託": 92,
    "其": 92,
    "粉": 92,
    "究": 91,
    "薦": 91,
    "動": 91,
    "扶": 91,
    "餅": 91,
    "蟻": 91,
    "壷": 91,
    "麓": 91,
    "簾": 90,
    "鋭": 89,
    "易": 89,
    "狐": 89,
    "彼": 89,
    "劉": 89,
    "飴": 88,
    "暦": 87,
    "寶": 87,
    "ド": 87,
    "佛": 86,
    "飽": 86,
    "毎": 86,
    "汲": 86,
    "底": 86,
    "デ": 85,
    "唄": 85,
    "賛": 85,
    "浄": 85,
    "辛": 85,
    "杢": 85,
    "栫": 85,
    "頓": 84,
    "蓼": 84,
    "疾": 83,
    "跳": 83,
    "曵": 83,
    "楼": 83,
    "詫": 83,
    "權": 83,
    "狹": 83,
    "崔": 83,
    "獅": 82,
    "役": 82,
    "億": 81,
    "珍": 81,
    "支": 81,
    "冷": 81,
    "禰": 81,
    "斧": 81,
    "株": 80,
    "鵬": 80,
    "且": 80,
    "楡": 80,
    "舶": 80,
    "供": 79,
    "蛇": 79,
    "杣": 79,
    "が": 79,
    "企": 78,
    "躍": 78,
    "徐": 78,
    "漢": 77,
    "側": 77,
    "菓": 75,
    "委": 75,
    "機": 75,
    "防": 75,
    "蝶": 75,
    "忽": 75,
    "枦": 75,
    "ャ": 75,
    "ビ": 75,
    "蜷": 74,
    "觜": 74,
    "虫": 74,
    "殊": 74,
    "柔": 74,
    "組": 74,
    "凡": 74,
    "調": 74,
    "栂": 74,
    "楳": 74,
    "監": 73,
    "潔": 73,
    "料": 73,
    "欠": 73,
    "ダ": 73,
    "寸": 72,
    "硲": 72,
    "塘": 72,
    "闘": 71,
    "精": 71,
    "戒": 71,
    "郭": 71,
    "續": 71,
    "蕉": 71,
    "鄭": 71,
    "芋": 70,
    "期": 70,
    "爲": 70,
    "密": 69,
    "挽": 69,
    "ソ": 69,
    "案": 68,
    "声": 68,
    "杭": 68,
    "膳": 68,
    "唱": 68,
    "壬": 68,
    "髭": 68,
    "鉾": 68,
    "巌": 67,
    "給": 67,
    "群": 67,
    "盟": 67,
    "材": 67,
    "鍜": 67,
    "団": 66,
    "窓": 66,
    "滴": 66,
    "衡": 66,
    "譜": 66,
    "乘": 66,
    "振": 66,
    "梯": 66,
    "兎": 66,
    "饒": 66,
    "發": 66,
    "鎖": 65,
    "渠": 65,
    "差": 65,
    "圖": 65,
    "垰": 65,
    "諫": 65,
    "微": 64,
    "丑": 64,
    "笘": 64,
    "靜": 64,
    "軸": 64,
    "問": 64,
    "捧": 64,
    "傍": 64,
    "姜": 64,
    "艶": 63,
    "眸": 63,
    "囿": 63,
    "ヨ": 63,
    "帖": 63,
    "櫨": 63,
    "壹": 63,
    "ネ": 63,
    "げ": 63,
    "趙": 63,
    "縫": 62,
    "参": 62,
    "柱": 62,
    "數": 62,
    "蘆": 62,
    "藝": 62,
    "姥": 61,
    "受": 61,
    "鮒": 61,
    "猶": 61,
    "騰": 61,
    "假": 61,
    "鰐": 60,
    "樅": 60,
    "把": 60,
    "求": 60,
    "書": 60,
    "柵": 60,
    "糀": 60,
    "模": 59,
    "告": 59,
    "釆": 59,
    "焼": 57,
    "煙": 57,
    "何": 57,
    "臨": 57,
    "頃": 57,
    "棋": 57,
    "梛": 57,
    "駄": 57,
    "鋪": 57,
    "韓": 57,
    "橿": 56,
    "兜": 56,
    "ぼ": 56,
    "背": 56,
    "判": 56,
    "碁": 56,
    "椚": 56,
    "抜": 55,
    "休": 55,
    "ズ": 55,
    "筆": 54,
    "恕": 54,
    "箇": 54,
    "悌": 54,
    "晝": 54,
    "藥": 54,
    "ブ": 54,
    "粒": 53,
    "礎": 53,
    "誼": 53,
    "帰": 53,
    "耳": 53,
    "兆": 53,
    "交": 53,
    "逹": 53,
    "性": 52,
    "鴛": 52,
    "陛": 52,
    "蔀": 52,
    "浴": 52,
    "藻": 52,
    "泥": 52,
    "團": 52,
    "贄": 52,
    "荏": 51,
    "釈": 51,
    "堪": 51,
    "栩": 51,
    "鋼": 50,
    "雀": 50,
    "他": 50,
    "懐": 50,
    "夷": 50,
    "磐": 50,
    "衞": 50,
    "拝": 49,
    "葦": 49,
    "説": 49,
    "樗": 49,
    "蕨": 49,
    "郞": 49,
    "亥": 48,
    "往": 48,
    "渦": 48,
    "肱": 48,
    "幣": 48,
    "弐": 48,
    "を": 47,
    "桔": 47,
    "導": 47,
    "濁": 47,
    "竪": 47,
    "儘": 47,
    "姿": 46,
    "怒": 46,
    "廿": 46,
    "協": 46,
    "緖": 46,
    "埼": 46,
    "論": 45,
    "漁": 45,
    "轡": 45,
    "舗": 45,
    "桟": 45,
    "斯": 45,
    "竿": 45,
    "楫": 45,
    "漸": 45,
    "解": 44,
    "鯛": 44,
    "構": 44,
    "乳": 44,
    "夘": 44,
    "巖": 44,
    "員": 44,
    "壺": 44,
    "癒": 44,
    "従": 43,
    "詳": 43,
    "卦": 43,
    "蛸": 43,
    "曹": 43,
    "莱": 43,
    "袰": 43,
    "」": 43,
    "肝": 43,
    "筏": 42,
    "撫": 42,
    "凉": 42,
    "壇": 42,
    "髪": 42,
    "滿": 42,
    "謡": 42,
    "ガ": 42,
    "蓋": 41,
    "奉": 41,
    "宋": 41,
    "款": 41,
    "習": 41,
    "溪": 41,
    "錠": 41,
    "傅": 41,
    "補": 40,
    "澗": 40,
    "狗": 40,
    "隣": 40,
    "配": 40,
    "濟": 40,
    "除": 39,
    "歴": 39,
    "碕": 39,
    "残": 39,
    "硫": 39,
    "雜": 39,
    "湾": 38,
    "杖": 38,
    "攻": 38,
    "致": 38,
    "鑑": 38,
    "去": 38,
    "制": 38,
    "蘓": 38,
    "拍": 38,
    "掠": 38,
    "尹": 38,
    "顯": 37,
    "餌": 37,
    "囲": 37,
    "着": 37,
    "筬": 37,
    "ァ": 37,
    "處": 36,
    "欄": 36,
    "勉": 36,
    "窄": 36,
    "榧": 36,
    "蠣": 36,
    "べ": 36,
    "県": 36,
    "巾": 35,
    "薪": 35,
    "衆": 35,
    "酢": 35,
    "遅": 35,
    "坐": 35,
    "呑": 35,
    "朗": 35,
    "曇": 34,
    "載": 34,
    "稼": 34,
    "画": 34,
    "ホ": 34,
    "掃": 34,
    "枇": 34,
    "陀": 34,
    "莊": 34,
    "埋": 34,
    "棗": 34,
    "均": 34,
    "収": 34,
    "ベ": 33,
    "摂": 33,
    "肖": 33,
    "推": 33,
    "産": 33,
    "鋸": 33,
    "勧": 33,
    "耆": 33,
    "超": 33,
    "標": 33,
    "壌": 33,
    "鉱": 33,
    "棒": 33,
    "枚": 33,
    "杤": 33,
    "甕": 33,
    "返": 33,
    "洌": 33,
    "奧": 33,
    "揺": 32,
    "グ": 32,
    "襟": 32,
    "講": 32,
    "殖": 32,
    "賜": 32,
    "証": 32,
    "繰": 32,
    "舌": 32,
    "朏": 32,
    "苧": 32,
    "授": 32,
    "酉": 32,
    "劔": 32,
    "逵": 32,
    "祉": 32,
    "遂": 32,
    "融": 32,
    "抄": 31,
    "穀": 31,
    "抱": 31,
    "感": 31,
    "岻": 31,
    "鐵": 31,
    "萓": 31,
    "固": 30,
    "竈": 30,
    "梗": 30,
    "掌": 30,
    "楚": 30,
    "峡": 30,
    "契": 30,
    "墳": 30,
    "録": 30,
    "ワ": 30,
    "怡": 30,
    "奇": 30,
    "董": 30,
    "硯": 30,
    "猫": 30,
    "葺": 29,
    "献": 29,
    "鞭": 29,
    "故": 29,
    "救": 29,
    "ぬ": 29,
    "脊": 29,
    "煤": 29,
    "繪": 29,
    "杷": 29,
    "－": 29,
    "バ": 29,
    "過": 28,
    "ざ": 28,
    "祇": 28,
    "径": 28,
    "業": 28,
    "帶": 28,
    "巡": 28,
    "涯": 28,
    "筈": 28,
    "彈": 28,
    "鱒": 28,
    "楜": 28,
    "餘": 28,
    "編": 28,
    "技": 28,
    "杠": 28,
    "机": 27,
    "茎": 27,
    "召": 27,
    "吐": 27,
    "羊": 27,
    "綛": 27,
    "蔡": 27,
    "鞘": 27,
    "詔": 26,
    "宕": 26,
    "鯵": 26,
    "盃": 26,
    "閏": 26,
    "蜜": 26,
    "竺": 26,
    "鍔": 26,
    "醇": 26,
    "放": 26,
    "淋": 26,
    "櫟": 26,
    "藺": 26,
    "秩": 26,
    "籐": 26,
    "泳": 26,
    "艸": 26,
    "存": 26,
    "螺": 25,
    "燕": 25,
    "街": 25,
    "妥": 25,
    "腸": 25,
    "盾": 25,
    "鯖": 25,
    "私": 25,
    "違": 25,
    "匹": 25,
    "績": 25,
    "楮": 25,
    "錫": 25,
    "柑": 25,
    "昻": 25,
    "弟": 25,
    "煌": 25,
    "欽": 25,
    "婦": 25,
    "稻": 25,
    "陪": 24,
    "讓": 24,
    "晒": 24,
    "迦": 24,
    "店": 24,
    "奬": 24,
    "顧": 24,
    "乕": 24,
    "奴": 24,
    "隨": 24,
    "濤": 24,
    "輕": 24,
    "鞆": 24,
    "宵": 23,
    "膓": 23,
    "併": 23,
    "整": 23,
    "兄": 23,
    "ゑ": 23,
    "摺": 23,
    "ザ": 23,
    "刻": 23,
    "璽": 23,
    "娘": 23,
    "揖": 23,
    "漣": 23,
    "峪": 23,
    "処": 23,
    "議": 23,
    "客": 23,
    "荊": 23,
    "棲": 23,
    "侯": 23,
    "岑": 23,
    "柞": 23,
    "攝": 22,
    "按": 22,
    "枕": 22,
    "蚊": 22,
    "苔": 22,
    "厩": 22,
    "皮": 22,
    "憶": 22,
    "馳": 22,
    "伺": 22,
    "釋": 22,
    "頴": 22,
    "糖": 22,
    "矛": 21,
    "眼": 21,
    "斑": 21,
    "肘": 21,
    "忰": 21,
    "篁": 21,
    "譽": 21,
    "萠": 21,
    "暸": 21,
    "赫": 21,
    "踊": 21,
    "挑": 21,
    "漠": 21,
    "勤": 20,
    "盆": 20,
    "移": 20,
    "撹": 20,
    "簡": 20,
    "肴": 20,
    "傘": 20,
    "爵": 20,
    "僧": 20,
    "槍": 20,
    "毒": 20,
    "岫": 20,
    "總": 20,
    "鎭": 20,
    "琥": 20,
    "枢": 20,
    "蛎": 20,
    "へ": 20,
    "翌": 20,
    "菩": 20,
    "呈": 20,
    "旨": 19,
    "閉": 19,
    "ヌ": 19,
    "伐": 19,
    "塊": 19,
    "曙": 19,
    "鎧": 19,
    "ゐ": 19,
    "慣": 19,
    "尺": 19,
    "旋": 19,
    "繕": 19,
    "亭": 19,
    "賞": 19,
    "侭": 19,
    "杁": 19,
    "帷": 19,
    "癸": 19,
    "鯰": 19,
    "麥": 19,
    "遍": 19,
    "裾": 19,
    "寬": 19,
    "賦": 19,
    "槁": 19,
    "系": 19,
    "検": 19,
    "ヴ": 19,
    "少": 19,
    "岨": 19,
    "廼": 19,
    "竃": 19,
    "鋳": 19,
    "専": 19,
    "娜": 19,
    "莖": 19,
    "砺": 19,
    "っ": 19,
    "穫": 18,
    "劍": 18,
    "謹": 18,
    "止": 18,
    "〆": 18,
    "ヘ": 18,
    "慕": 18,
    "枩": 18,
    "雌": 18,
    "哀": 18,
    "鐙": 18,
    "事": 18,
    "茗": 18,
    "化": 18,
    "收": 18,
    "蕎": 18,
    "招": 18,
    "昊": 18,
    "珊": 18,
    "劒": 18,
    "戌": 18,
    "覺": 17,
    "雉": 17,
    "ゴ": 17,
    "特": 17,
    "校": 17,
    "刃": 17,
    "姓": 17,
    "棹": 17,
    "擁": 17,
    "限": 17,
    "暎": 17,
    "採": 17,
    "炎": 17,
    "鮮": 17,
    "萢": 17,
    "‐": 17,
    "遣": 17,
    "亙": 17,
    "犀": 17,
    "歯": 17,
    "樟": 17,
    "孕": 17,
    "随": 16,
    "鰭": 16,
    "負": 16,
    "趣": 16,
    "障": 16,
    "儒": 16,
    "般": 16,
    "穰": 16,
    "橡": 16,
    "涙": 16,
    "鰺": 16,
    "封": 16,
    "硝": 16,
    "確": 16,
    "洙": 16,
    "援": 16,
    "頂": 16,
    "霍": 16,
    "ギ": 16,
    "粧": 16,
    "賣": 16,
    "拜": 16,
    "莇": 15,
    "競": 15,
    "從": 15,
    "頑": 15,
    "顔": 15,
    "寮": 15,
    "誘": 15,
    "沈": 15,
    "涛": 15,
    "買": 15,
    "符": 15,
    "椹": 15,
    "泓": 15,
    "稟": 15,
    "馴": 15,
    "幼": 15,
    "祁": 15,
    "鶏": 15,
    "都": 15,
    "ぴ": 15,
    "絆": 15,
    "ぽ": 15,
    "廷": 15,
    "秡": 15,
    "鱸": 15,
    "漉": 14,
    "駕": 14,
    "鋒": 14,
    "耐": 14,
    "列": 14,
    "象": 14,
    "峽": 14,
    "選": 14,
    "抽": 14,
    "効": 14,
    "濡": 14,
    "賊": 14,
    "粹": 14,
    "離": 14,
    "答": 14,
    "譯": 14,
    "哘": 14,
    "盧": 14,
    "ヲ": 13,
    "稿": 13,
    "慰": 13,
    "閣": 13,
    "披": 13,
    "蝉": 13,
    "聴": 13,
    "屏": 13,
    "腹": 13,
    "挾": 13,
    "槐": 13,
    "疇": 13,
    "磧": 13,
    "鵤": 13,
    "皷": 13,
    "悪": 13,
    "プ": 13,
    "淨": 13,
    "拾": 13,
    "拂": 13,
    "胸": 13,
    "還": 13,
    "玻": 13,
    "算": 13,
    "蒋": 13,
    "賓": 13,
    "薹": 13,
    "潘": 13,
    "稙": 13,
    "旻": 13,
    "悴": 12,
    "罍": 12,
    "朕": 12,
    "漫": 12,
    "鮭": 12,
    "旧": 12,
    "帥": 12,
    "鴈": 12,
    "栽": 12,
    "堆": 12,
    "弧": 12,
    "學": 12,
    "諮": 12,
    "捨": 12,
    "勒": 12,
    "吽": 12,
    "寉": 12,
    "枌": 12,
    "鶉": 12,
    "パ": 12,
    "候": 12,
    "广": 12,
    "繩": 12,
    "苦": 12,
    "ゼ": 12,
    "肩": 12,
    "祷": 12,
    "訳": 12,
    "辨": 12,
    "戀": 12,
    "禾": 11,
    "級": 11,
    "率": 11,
    "復": 11,
    "蹴": 11,
    "縮": 11,
    "第": 11,
    "搗": 11,
    "演": 11,
    "鳶": 11,
    "肆": 11,
    "苣": 11,
    "鳫": 11,
    "抹": 11,
    "夾": 11,
    "医": 11,
    "帽": 11,
    "営": 11,
    "墓": 11,
    "胆": 11,
    "魂": 11,
    "革": 11,
    "珂": 11,
    "晦": 11,
    "珉": 11,
    "喉": 11,
    "審": 11,
    "回": 11,
    "墻": 11,
    "突": 11,
    "窟": 11,
    "驛": 11,
    "曄": 11,
    "叙": 11,
    "嶝": 11,
    "圃": 11,
    "檪": 11,
    "簀": 11,
    "苺": 11,
    "塑": 11,
    "奕": 11,
    "序": 10,
    "眉": 10,
    "ボ": 10,
    "壘": 10,
    "祿": 10,
    "ゲ": 10,
    "党": 10,
    "派": 10,
    "廊": 10,
    "肌": 10,
    "蝋": 10,
    "眺": 10,
    "箟": 10,
    "霊": 10,
    "媚": 10,
    "犹": 10,
    "祓": 10,
    "述": 10,
    "舍": 10,
    "桓": 10,
    "枯": 10,
    "鉛": 10,
    "項": 10,
    "炫": 10,
    "煥": 10,
    "炯": 10,
    "狛": 10,
    "杞": 10,
    "晄": 10,
    "夲": 10,
    "牙": 10,
    "撰": 10,
    "珀": 10,
    "櫓": 10,
    "塀": 10,
    "騨": 10,
    "仏": 10,
    "徃": 10,
    "杼": 10,
    "柤": 10,
    "欅": 10,
    "澳": 10,
    "獨": 10,
    "禹": 10,
    "觸": 10,
    "馮": 10,
    "熨": 10,
    "齎": 10,
    "釡": 10,
    "靡": 10,
    "売": 9,
    "貸": 9,
    "謄": 9,
    "黍": 9,
    "撤": 9,
    "岱": 9,
    "胎": 9,
    "卷": 9,
    "畳": 9,
    "裳": 9,
    "臥": 9,
    "投": 9,
    "梃": 9,
    "秤": 9,
    "矯": 9,
    "矧": 9,
    "隻": 9,
    "桾": 9,
    "竝": 9,
    "粳": 9,
    "踏": 9,
    "ピ": 9,
    "琪": 9,
    "茲": 9,
    "忌": 9,
    "躬": 9,
    "墾": 9,
    "鎬": 9,
    "濯": 9,
    "絡": 9,
    "赦": 9,
    "蒐": 9,
    "猟": 9,
    "駈": 9,
    "昔": 9,
    "搭": 9,
    "慵": 9,
    "傷": 9,
    "題": 9,
    "崩": 9,
    "椀": 9,
    "兪": 9,
    "猩": 9,
    "礪": 9,
    "筌": 9,
    "經": 9,
    "鬮": 9,
    "牡": 9,
    "値": 9,
    "孤": 9,
    "菴": 9,
    "乱": 9,
    "局": 9,
    "ゃ": 9,
    "漕": 8,
    "循": 8,
    "褒": 8,
    "硬": 8,
    "誕": 8,
    "籬": 8,
    "躰": 8,
    "筥": 8,
    "独": 8,
    "榔": 8,
    "膝": 8,
    "蔓": 8,
    "再": 8,
    "堵": 8,
    "僑": 8,
    "駅": 8,
    "鈎": 8,
    "魔": 8,
    "挟": 8,
    "弁": 8,
    "笥": 8,
    "脱": 8,
    "搖": 8,
    "血": 8,
    "睿": 8,
    "渊": 8,
    "芭": 8,
    "楞": 8,
    "縞": 8,
    "勾": 8,
    "芯": 8,
    "娟": 8,
    "ペ": 8,
    "鑪": 8,
    "評": 8,
    "揃": 8,
    "捕": 8,
    "狼": 8,
    "異": 8,
    "班": 8,
    "櫂": 8,
    "害": 8,
    "裸": 8,
    "妍": 8,
    "雙": 8,
    "姚": 8,
    "枋": 8,
    "畚": 8,
    "袁": 8,
    "譚": 8,
    "豐": 8,
    "黨": 8,
    "斜": 8,
    "襲": 8,
    "域": 8,
    "蕃": 8,
    "嘴": 8,
    "繋": 8,
    "鱗": 8,
    "幻": 8,
    "錢": 8,
    "遮": 8,
    "読": 8,
    "簔": 8,
    "俟": 7,
    "糊": 7,
    "幌": 7,
    "批": 7,
    "席": 7,
    "装": 7,
    "挺": 7,
    "ヰ": 7,
    "硴": 7,
    "鎰": 7,
    "鳰": 7,
    "麝": 7,
    "否": 7,
    "ぃ": 7,
    "焔": 7,
    "庶": 7,
    "「": 7,
    "索": 7,
    "藩": 7,
    "絞": 7,
    "燒": 7,
    "麹": 7,
    "括": 7,
    "悉": 7,
    "杓": 7,
    "商": 7,
    "燃": 7,
    "遇": 7,
    "散": 7,
    "浬": 7,
    "属": 7,
    "謠": 7,
    "炮": 7,
    "ォ": 7,
    "需": 7,
    "晩": 7,
    "邵": 7,
    "培": 7,
    "腕": 7,
    "于": 7,
    "楸": 7,
    "汪": 7,
    "疊": 7,
    "瘧": 7,
    "薊": 7,
    "鰕": 7,
    "鷦": 7,
    "鷯": 7,
    "綴": 7,
    "閤": 7,
    "渭": 7,
    "析": 7,
    "惺": 7,
    "戝": 7,
    "凰": 7,
    "曰": 7,
    "翰": 7,
    "ﾉ": 6,
    "檗": 6,
    "醉": 6,
    "適": 6,
    "例": 6,
    "脚": 6,
    "庚": 6,
    "裁": 6,
    "炉": 6,
    "鐸": 6,
    "粛": 6,
    "箆": 6,
    "祗": 6,
    "纓": 6,
    "艫": 6,
    "薛": 6,
    "陌": 6,
    "ポ": 6,
    "酸": 6,
    "糧": 6,
    "鰻": 6,
    "桍": 6,
    "覽": 6,
    "涵": 6,
    "吸": 6,
    "潰": 6,
    "注": 6,
    "艘": 6,
    "穎": 6,
    "戯": 6,
    "谿": 6,
    "写": 6,
    "朶": 6,
    "状": 6,
    "杲": 6,
    "個": 6,
    "邸": 6,
    "樵": 6,
    "阜": 6,
    "唆": 6,
    "舒": 6,
    "靭": 6,
    "看": 6,
    "凍": 6,
    "鑄": 6,
    "談": 6,
    "ぇ": 6,
    "禿": 6,
    "聲": 6,
    "庇": 6,
    "恆": 6,
    "瓢": 6,
    "隋": 6,
    "螢": 6,
    "魯": 6,
    "枠": 6,
    "冲": 6,
    "咸": 6,
    "廖": 6,
    "決": 6,
    "拔": 6,
    "糴": 6,
    "鮑": 6,
    "鴉": 6,
    "掬": 6,
    "俄": 6,
    "扉": 6,
    "肯": 6,
    "鈷": 6,
    "ゥ": 6,
    "泡": 6,
    "枳": 6,
    "験": 6,
    "俳": 6,
    "ヱ": 6,
    "接": 6,
    "恐": 6,
    "舖": 6,
    "圍": 6,
    "柁": 6,
    "捻": 6,
    "琶": 6,
    "殷": 6,
    "鉈": 6,
    "ぢ": 5,
    "郊": 5,
    "煎": 5,
    "雇": 5,
    "盡": 5,
    "煇": 5,
    "号": 5,
    "ぷ": 5,
    "聚": 5,
    "体": 5,
    "竒": 5,
    "獺": 5,
    "皀": 5,
    "觀": 5,
    "閨": 5,
    "鬢": 5,
    "麸": 5,
    "萎": 5,
    "苛": 5,
    "碵": 5,
    "核": 5,
    "峩": 5,
    "廸": 5,
    "嚴": 5,
    "瑩": 5,
    "禧": 5,
    "邪": 5,
    "剌": 5,
    "鍾": 5,
    "潴": 5,
    "隹": 5,
    "槫": 5,
    "鉦": 5,
    "榁": 5,
    "ぁ": 5,
    "据": 5,
    "毋": 5,
    "齢": 5,
    "戴": 5,
    "湛": 5,
    "倶": 5,
    "娥": 5,
    "袮": 5,
    "甑": 5,
    "盈": 5,
    "鎚": 5,
    "諾": 5,
    "梼": 5,
    "椴": 5,
    "ゞ": 5,
    "珎": 5,
    "偕": 5,
    "兀": 5,
    "圦": 5,
    "埒": 5,
    "墫": 5,
    "弭": 5,
    "戍": 5,
    "橙": 5,
    "歸": 5,
    "淤": 5,
    "淮": 5,
    "篝": 5,
    "糺": 5,
    "莅": 5,
    "螻": 5,
    "迚": 5,
    "閔": 5,
    "魏": 5,
    "寝": 5,
    "屈": 5,
    "締": 5,
    "楪": 5,
    "轉": 5,
    "鉤": 5,
    "姶": 5,
    "４": 5,
    "ヅ": 5,
    "讀": 5,
    "凝": 5,
    "菲": 5,
    "翫": 5,
    "膽": 5,
    "電": 5,
    "垠": 5,
    "洒": 5,
    "醤": 5,
    "琵": 5,
    "侘": 5,
    "衷": 5,
    "酌": 5,
    "霖": 5,
    "ゾ": 5,
    "邱": 5,
    "軣": 4,
    "弗": 4,
    "終": 4,
    "震": 4,
    "椽": 4,
    "討": 4,
    "肉": 4,
    "湶": 4,
    "磴": 4,
    "耿": 4,
    "脛": 4,
    "莨": 4,
    "鄒": 4,
    "鉞": 4,
    "鶸": 4,
    "鼡": 4,
    "欲": 4,
    "胃": 4,
    "臭": 4,
    "噌": 4,
    "輩": 4,
    "偵": 4,
    "卿": 4,
    "崖": 4,
    "抗": 4,
    "蓍": 4,
    "剰": 4,
    "慮": 4,
    "聰": 4,
    "質": 4,
    "瑜": 4,
    "撞": 4,
    "汎": 4,
    "牲": 4,
    "杳": 4,
    "漏": 4,
    "態": 4,
    "匤": 4,
    "蒿": 4,
    "鹽": 4,
    "鉉": 4,
    "懍": 4,
    "昨": 4,
    "警": 4,
    "約": 4,
    "碑": 4,
    "貨": 4,
    "践": 4,
    "赴": 4,
    "屁": 4,
    "握": 4,
    "悧": 4,
    "刎": 4,
    "卞": 4,
    "哥": 4,
    "垪": 4,
    "幟": 4,
    "枷": 4,
    "柬": 4,
    "檮": 4,
    "炬": 4,
    "粢": 4,
    "舊": 4,
    "遲": 4,
    "閼": 4,
    "鰤": 4,
    "鷄": 4,
    "鰯": 4,
    "匝": 4,
    "必": 4,
    "筱": 4,
    "艾": 4,
    "范": 4,
    "酵": 4,
    "艦": 4,
    "遷": 4,
    "佩": 4,
    "俐": 4,
    "埈": 4,
    "兌": 4,
    "杯": 4,
    "丙": 4,
    "嫁": 4,
    "酔": 4,
    "銃": 4,
    "拮": 4,
    "箙": 4,
    "偸": 4,
    "沛": 4,
    "頗": 4,
    "叉": 4,
    "宴": 4,
    "鼎": 4,
    "椢": 4,
    "輻": 4,
    "急": 4,
    "報": 4,
    "醸": 4,
    "退": 3,
    "銑": 3,
    "劾": 3,
    "湟": 3,
    "探": 3,
    "炊": 3,
    "糾": 3,
    "瀚": 3,
    "秘": 3,
    "便": 3,
    "崟": 3,
    "綟": 3,
    "徴": 3,
    "皋": 3,
    "鑰": 3,
    "様": 3,
    "預": 3,
    "汽": 3,
    "茹": 3,
    "襖": 3,
    "翻": 3,
    "皃": 3,
    "履": 3,
    "殻": 3,
    "鰍": 3,
    "汗": 3,
    "惑": 3,
    "丿": 3,
    "憐": 3,
    "貿": 3,
    "誡": 3,
    "卑": 3,
    "炳": 3,
    "而": 3,
    "認": 3,
    "控": 3,
    "椅": 3,
    "驚": 3,
    "缶": 3,
    "艮": 3,
    "屯": 3,
    "衢": 3,
    "届": 3,
    "昏": 3,
    "恍": 3,
    "苙": 3,
    "蒸": 3,
    "飾": 3,
    "鈍": 3,
    "夙": 3,
    "冒": 3,
    "撲": 3,
    "嬌": 3,
    "卸": 3,
    "它": 3,
    "陏": 3,
    "磋": 3,
    "獎": 3,
    "碗": 3,
    "逓": 3,
    "払": 3,
    "陦": 3,
    "庁": 3,
    "銚": 3,
    "妤": 3,
    "菟": 3,
    "哩": 3,
    "区": 3,
    "俸": 3,
    "敵": 3,
    "杰": 3,
    "呰": 3,
    "坡": 3,
    "奚": 3,
    "專": 3,
    "峙": 3,
    "嶬": 3,
    "攪": 3,
    "旛": 3,
    "柆": 3,
    "渾": 3,
    "畫": 3,
    "瞰": 3,
    "耘": 3,
    "臂": 3,
    "裙": 3,
    "珈": 3,
    "銕": 3,
    "錺": 3,
    "鑢": 3,
    "鈩": 3,
    "狄": 3,
    "塒": 3,
    "戦": 3,
    "蹄": 3,
    "著": 3,
    "勺": 3,
    "冥": 3,
    "凾": 3,
    "箒": 3,
    "垢": 3,
    "愈": 3,
    "輸": 3,
    "鰹": 3,
    "喚": 3,
    "卒": 3,
    "虞": 3,
    "寂": 3,
    "勳": 3,
    "弊": 3,
    "潦": 3,
    "闌": 3,
    "筍": 3,
    "叫": 3,
    "冊": 3,
    "晙": 3,
    "壤": 3,
    "駱": 3,
    "鮓": 3,
    "浚": 3,
    "瀟": 3,
    "ぜ": 3,
    "蕊": 3,
    "褝": 3,
    "敍": 3,
    "斌": 3,
    "楷": 3,
    "溶": 3,
    "課": 3,
    "檎": 3,
    "衝": 3,
    "触": 3,
    "堕": 3,
    "線": 3,
    "聆": 3,
    "篦": 3,
    "低": 3,
    "転": 3,
    "暑": 3,
    "磁": 3,
    "察": 3,
    "非": 3,
    "簿": 3,
    "兔": 3,
    "莵": 3,
    "ゝ": 3,
    "娑": 3,
    "漂": 3,
    "祟": 3,
    "沁": 3,
    "彭": 3,
    "瞿": 3,
    "豕": 3,
    "賈": 3,
    "檐": 2,
    "脈": 2,
    "掲": 2,
    "宦": 2,
    "試": 2,
    "繊": 2,
    "廬": 2,
    "徂": 2,
    "徠": 2,
    "暈": 2,
    "枅": 2,
    "櫁": 2,
    "猜": 2,
    "鴾": 2,
    "価": 2,
    "既": 2,
    "辞": 2,
    "乞": 2,
    "杆": 2,
    "隊": 2,
    "拘": 2,
    "僖": 2,
    "減": 2,
    "琇": 2,
    "曠": 2,
    "莪": 2,
    "酷": 2,
    "況": 2,
    "諠": 2,
    "熹": 2,
    "咏": 2,
    "坤": 2,
    "繚": 2,
    "廏": 2,
    "穹": 2,
    "殉": 2,
    "俚": 2,
    "黙": 2,
    "術": 2,
    "該": 2,
    "稱": 2,
    "霆": 2,
    "档": 2,
    "叮": 2,
    "簇": 2,
    "栓": 2,
    "湫": 2,
    "即": 2,
    "翊": 2,
    "蜘": 2,
    "茸": 2,
    "塞": 2,
    "乎": 2,
    "薰": 2,
    "醒": 2,
    "濘": 2,
    "週": 2,
    "禪": 2,
    "券": 2,
    "遁": 2,
    "畷": 2,
    "剥": 2,
    "莫": 2,
    "紐": 2,
    "鋲": 2,
    "職": 2,
    "変": 2,
    "篇": 2,
    "亢": 2,
    "牝": 2,
    "襌": 2,
    "幽": 2,
    "炅": 2,
    "綵": 2,
    "韶": 2,
    "莎": 2,
    "亟": 2,
    "勵": 2,
    "營": 2,
    "誾": 2,
    "廳": 2,
    "棡": 2,
    "棯": 2,
    "淪": 2,
    "瀉": 2,
    "礫": 2,
    "糒": 2,
    "糯": 2,
    "翆": 2,
    "苞": 2,
    "萇": 2,
    "蟇": 2,
    "珪": 2,
    "鐡": 2,
    "鑛": 2,
    "隴": 2,
    "餝": 2,
    "鶺": 2,
    "焏": 2,
    "窺": 2,
    "液": 2,
    "吝": 2,
    "侶": 2,
    "療": 2,
    "屑": 2,
    "纒": 2,
    "帳": 2,
    "悳": 2,
    "拇": 2,
    "槿": 2,
    "笆": 2,
    "茆": 2,
    "貍": 2,
    "貮": 2,
    "躑": 2,
    "鞁": 2,
    "怙": 2,
    "溢": 2,
    "裡": 2,
    "乢": 2,
    "沿": 2,
    "悼": 2,
    "燮": 2,
    "瀛": 2,
    "屹": 2,
    "逧": 2,
    "?": 2,
    "麒": 2,
    "蟲": 2,
    "叔": 2,
    "璟": 2,
    "籍": 2,
    "壕": 2,
    "獄": 2,
    "湲": 2,
    "濫": 2,
    "姪": 2,
    "蓙": 2,
    "艇": 2,
    "臻": 2,
    "焦": 2,
    "眠": 2,
    "峅": 2,
    "絲": 2,
    "熟": 2,
    "製": 2,
    "査": 2,
    "椨": 2,
    "槝": 2,
    "鄙": 2,
    "含": 2,
    "韵": 2,
    "祺": 2,
    "宸": 2,
    "碆": 2,
    "軟": 2,
    "倩": 2,
    "７": 2,
    "懇": 2,
    "潜": 2,
    "催": 2,
    "侖": 2,
    "柀": 2,
    "熈": 2,
    "羚": 2,
    "湘": 2,
    "抦": 2,
    "粗": 2,
    "鎔": 2,
    "狸": 2,
    "単": 2,
    "喆": 2,
    "曦": 2,
    "榴": 2,
    "這": 2,
    "曼": 2,
    "淙": 2,
    "憙": 2,
    "埓": 2,
    "嵒": 2,
    "徑": 2,
    "矮": 2,
    "芟": 2,
    "裴": 2,
    "鶯": 2,
    "盥": 2,
    "銖": 2,
    "贈": 2,
    "頻": 2,
    "敞": 2,
    "棕": 2,
    "攵": 2,
    "倹": 2,
    "咩": 2,
    "爍": 2,
    "描": 2,
    "胴": 2,
    "冢": 2,
    "晴": 2,
    "寢": 2,
    "緤": 2,
    "沸": 2,
    "尤": 2,
    "葎": 2,
    "儁": 2,
    "咄": 2,
    "揉": 2,
    "樊": 2,
    "狢": 2,
    "瓊": 2,
    "萃": 2,
    "闕": 2,
    "靱": 2,
    "鬚": 2,
    "麩": 2,
    "皛": 2,
    "睡": 2,
    "毘": 2,
    "ﾂ": 2,
    "纏": 2,
    "栴": 2,
    "。": 2,
    "渟": 2,
    "＆": 2,
    "秉": 2,
    "倪": 2,
    "碣": 2,
    "舂": 2,
    "※": 1,
    "麼": 1,
    "蛙": 1,
    "孜": 1,
    "爆": 1,
    "搆": 1,
    "瀑": 1,
    "燧": 1,
    "莢": 1,
    "筵": 1,
    "勿": 1,
    "輌": 1,
    "逑": 1,
    "擧": 1,
    "―": 1,
    "３": 1,
    "巒": 1,
    "獲": 1,
    "虜": 1,
    "邇": 1,
    "喨": 1,
    "霸": 1,
    "攸": 1,
    "鑽": 1,
    "鑚": 1,
    "躯": 1,
    "嘯": 1,
    "幤": 1,
    "遺": 1,
    "傭": 1,
    "弍": 1,
    "軼": 1,
    "": 1,
    "鉐": 1,
    "縺": 1,
    "搦": 1,
    "陞": 1,
    "恂": 1,
    "刊": 1,
    "汝": 1,
    "歟": 1,
    "尢": 1,
    "貰": 1,
    "气": 1,
    "娃": 1,
    "衰": 1,
    "ｚ": 1,
    "瑟": 1,
    "迯": 1,
    "竟": 1,
    "Ｋ": 1,
    "檸": 1,
    "縷": 1,
    "Ｗ": 1,
    "鼠": 1,
    "蕾": 1,
    "憎": 1,
    "坦": 1,
    "蛛": 1,
    "崋": 1,
    "轍": 1,
    "妬": 1,
    "撃": 1,
    "誄": 1,
    "檻": 1,
    "淘": 1,
    "妊": 1,
    "坏": 1,
    "悲": 1,
    "鉋": 1,
    "死": 1,
    "靖": 1,
    "奮": 1,
    "縹": 1,
    "　": 1,
    "讚": 1,
    "燻": 1,
    "繼": 1,
    "迷": 1,
    "闇": 1,
    "刕": 1,
    "霓": 1,
    "薇": 1,
    "窈": 1,
    "腱": 1,
    "楨": 1,
    "Ｔ": 1,
    "Ｎ": 1,
    "婁": 1,
    "匆": 1,
    "叺": 1,
    "憮": 1,
    "擲": 1,
    "朧": 1,
    "朿": 1,
    "楾": 1,
    "檍": 1,
    "檢": 1,
    "歡": 1,
    "泙": 1,
    "壊": 1,
    "濮": 1,
    "瀋": 1,
    "甃": 1,
    "盻": 1,
    "稈": 1,
    "稾": 1,
    "粱": 1,
    "耜": 1,
    "肬": 1,
    "儿": 1,
    "裨": 1,
    "觴": 1,
    "譛": 1,
    "賁": 1,
    "賤": 1,
    "錣": 1,
    "鐃": 1,
    "阮": 1,
    "陬": 1,
    "靹": 1,
    "鱧": 1,
    "增": 1,
    "樰": 1,
    "綷": 1,
    "葈": 1,
    "鴎": 1,
    "蚋": 1,
    "巫": 1,
    "祀": 1,
    "媒": 1,
    "埣": 1,
    "娚": 1,
    "緞": 1,
    "猗": 1,
    "蚫": 1,
    "躅": 1,
    "麋": 1,
    "歐": 1,
    "綠": 1,
    "驗": 1,
    "膠": 1,
    "鷓": 1,
    "褐": 1,
    "寰": 1,
    "烱": 1,
    "概": 1,
    "呆": 1,
    "幺": 1,
    "臧": 1,
    "１": 1,
    "肢": 1,
    "侊": 1,
    "軾": 1,
    "誤": 1,
    "僮": 1,
    "倞": 1,
    "昧": 1,
    "掻": 1,
    "或": 1,
    "翡": 1,
    "葆": 1,
    "喝": 1,
    "冽": 1,
    "賄": 1,
    "贇": 1,
    "奔": 1,
    "怏": 1,
    "頸": 1,
    "失": 1,
    "燁": 1,
    "錘": 1,
    "蔗": 1,
    "酬": 1,
    "暫": 1,
    "函": 1,
    "縵": 1,
    "脾": 1,
    "騏": 1,
    "俉": 1,
    "詐": 1,
    "茱": 1,
    "隔": 1,
    "６": 1,
    "責": 1,
    "頁": 1,
    "拙": 1,
    "械": 1,
    "昮": 1,
    "珸": 1,
    "畿": 1,
    "焄": 1,
    "戈": 1,
    "駛": 1,
    "倣": 1,
    "斤": 1,
    "携": 1,
    "嬰": 1,
    "跨": 1,
    "閲": 1,
    "莠": 1,
    "悛": 1,
    "慨": 1,
    "諦": 1,
    "顆": 1,
    "ｖ": 1,
    "挌": 1,
    "熾": 1,
    "穩": 1,
    "尖": 1,
    "租": 1,
    "剪": 1,
    "損": 1,
    "滄": 1,
    "墅": 1,
    "漬": 1,
    "砲": 1,
    "Ｌ": 1,
    "淫": 1,
    "迭": 1,
    "婿": 1,
    "諳": 1,
    "罹": 1,
    "ｯ": 1,
    "怖": 1,
    "舷": 1,
    "駮": 1,
    "抖": 1,
    "昶": 1,
    "夭": 1,
    "沫": 1,
    "熏": 1,
    "霙": 1,
    "淏": 1,
    "揆": 1,
    "衍": 1,
    "芬": 1,
    "濬": 1,
    "倬": 1,
    "痲": 1,
    "喩": 1,
    "埀": 1,
    "壼": 1,
    "寔": 1,
    "換": 1,
    "屶": 1,
    "岶": 1,
    "怱": 1,
    "桴": 1,
    "慇": 1,
    "葱": 1,
    "贊": 1,
    "溥": 1,
    "猊": 1,
    "罟": 1,
    "聳": 1,
    "莚": 1,
    "蠏": 1,
    "貳": 1,
    "懋": 1,
    "閠": 1,
    "鹵": 1,
    "鼈": 1,
    "嵓": 1,
    "鄧": 1,
    "偶": 1,
    "ぱ": 1,
    "件": 1,
    "腐": 1,
    "簸": 1,
    "冀": 1,
    "槲": 1,
    "笊": 1,
    "颪": 1,
    "畏": 1,
    "瀞": 1,
    "琿": 1,
    "逐": 1,
    "瀾": 1,
    "謂": 1,
    "骨": 1,
    "燥": 1,
    "暇": 1,
    "耽": 1,
    "淇": 1,
    "臓": 1,
    "俤": 1,
    "逞": 1,
    "丕": 1,
    "楹": 1,
    "鍈": 1,
    "潭": 1,
    "錡": 1,
    "夋": 1,
    "佚": 1,
    "荅": 1,
    "霈": 1,
    "慌": 1,
    "澈": 1,
    "蚕": 1,
    "迺": 1,
    "餐": 1,
    "晤": 1,
    "麾": 1,
    "蝮": 1,
    "嫡": 1,
    "迴": 1,
    "呀": 1,
    "鈞": 1,
    "葩": 1,
    "嚢": 1,
    "掫": 1,
    "？": 1,
    "ｋ": 1,
    "錆": 1,
    "賎": 1,
    "頤": 1,
    "靫": 1,
    "摸": 1,
    "遜": 1,
    "釉": 1,
    "亰": 1,
    "嬢": 1,
    "慢": 1,
    "訶": 1,
    "嘩": 1,
    "磊": 1,
    "昿": 1,
    "擢": 1,
    "巍": 1,
    "諺": 1,
    "巷": 1,
    "祕": 1,
    "話": 1,
    "担": 1,
    "禛": 1,
    "樌": 1,
    "蛤": 1,
    "虚": 1,
    "覆": 1,
    "驥": 1,
    "悸": 1,
    "蹊": 1,
    "云": 1,
    "孑": 1,
    "ぺ": 1,
    "拷": 1,
    "煉": 1,
    "膺": 1,
    "尓": 1,
    "佗": 1,
    "偖": 1,
    "僊": 1,
    "勸": 1,
    "卉": 1,
    "孰": 1,
    "惡": 1,
    "旙": 1,
    "柧": 1,
    "棧": 1,
    "椪": 1,
    "乂": 1,
    "樒": 1,
    "汾": 1,
    "游": 1,
    "爰": 1,
    "畭": 1,
    "竇": 1,
    "笵": 1,
    "襭": 1,
    "芒": 1,
    "苻": 1,
    "莟": 1,
    "蒹": 1,
    "暄": 1,
    "溟": 1,
    "轆": 1,
    "轤": 1,
    "韋": 1,
    "鰈": 1,
    "鰰": 1,
    "鶫": 1,
    "鷭": 1,
    "硤": 1,
    "﨟": 1,
    "鵫": 1,
    "蘿": 1,
    "葡": 1,
    "萄": 1,
    "垳": 1,
    "捶": 1,
    "泗": 1,
    "緇": 1,
    "鷁": 1,
    "咽": 1,
    "烽": 1,
    "恥": 1,
    "鑒": 1,
    "胱": 1,
    "纖": 1,
    "袷": 1,
    "崗": 1,
    "ﾄ": 1,
    "ｲ": 1,
    "琮": 1,
    "樓": 1,
    "昱": 1,
    "劫": 1,
    "牀": 1,
    "＋": 1,
    "罷": 1,
    "粲": 1,
    "斬": 1,
    "匯": 1,
    "誥": 1,
    "鰲": 1,
    "醜": 1,
    "縒": 1,
    "￥": 1,
    "刹": 1,
    "病": 1,
    "疎": 1,
    "梦": 1,
    "宛": 1,
    "糎": 1,
    "ぅ": 1,
    "：": 1,
    "賃": 1,
    "燐": 1,
    "仟": 1,
    "霏": 1,
    "頡": 1,
    "ぉ": 1,
    "窯": 1,
    "迩": 1,
    "掉": 1,
    "蝿": 1,
    "溌": 1,
    "錨": 1,
    "厦": 1,
    "戊": 1,
    "扎": 1,
    "晞": 1,
    "嫻": 1,
    "蓁": 1,
    "晉": 1,
    "晰": 1,
    "嫣": 1,
    "琦": 1,
    "厂": 1,
    "倚": 1,
    "哈": 1,
    "註": 1,
    "幢": 1,
    "戛": 1,
    "戰": 1,
    "抓": 1,
    "浣": 1,
    "涸": 1,
    "灌": 1,
    "澀": 1,
    "烟": 1,
    "烝": 1,
    "犂": 1,
    "畴": 1,
    "腮": 1,
    "藜": 1,
    "誂": 1,
    "踞": 1,
    "忻": 1,
    "釖": 1,
    "ヂ": 1,
    "餠": 1,
    "黌": 1,
    "逸": 1
}